{
  "id": "c5beec59-2b88-4f3f-ba35-7640a58a9ba6",
  "revision": 0,
  "last_node_id": 196,
  "last_link_id": 235,
  "nodes": [
    {
      "id": 190,
      "type": "ConditioningZeroOut",
      "pos": [
        -76.21748617376097,
        379.38171365449824
      ],
      "size": [
        197.712890625,
        26
      ],
      "flags": {
        "collapsed": false
      },
      "order": 7,
      "mode": 0,
      "inputs": [
        {
          "name": "conditioning",
          "type": "CONDITIONING",
          "link": 219
        }
      ],
      "outputs": [
        {
          "name": "CONDITIONING",
          "type": "CONDITIONING",
          "links": [
            220
          ]
        }
      ],
      "properties": {
        "cnr_id": "comfy-core",
        "ver": "0.3.76",
        "Node name for S&R": "ConditioningZeroOut"
      },
      "widgets_values": []
    },
    {
      "id": 164,
      "type": "VAEDecode",
      "pos": [
        455.7269386124458,
        280.34970420475
      ],
      "size": [
        140,
        46
      ],
      "flags": {
        "collapsed": false
      },
      "order": 9,
      "mode": 0,
      "inputs": [
        {
          "name": "samples",
          "type": "LATENT",
          "link": 187
        },
        {
          "name": "vae",
          "type": "VAE",
          "link": 233
        }
      ],
      "outputs": [
        {
          "name": "IMAGE",
          "type": "IMAGE",
          "links": [
            201
          ]
        }
      ],
      "properties": {
        "cnr_id": "comfy-core",
        "ver": "0.3.32",
        "Node name for S&R": "VAEDecode"
      },
      "widgets_values": []
    },
    {
      "id": 171,
      "type": "SaveImage",
      "pos": [
        621.8720834002202,
        283.02547473527426
      ],
      "size": [
        615.0020278469565,
        679.2872229947789
      ],
      "flags": {},
      "order": 10,
      "mode": 0,
      "inputs": [
        {
          "name": "images",
          "type": "IMAGE",
          "link": 201
        }
      ],
      "outputs": [],
      "title": "Save Image Original",
      "properties": {
        "cnr_id": "comfy-core",
        "ver": "0.3.27",
        "Node name for S&R": "SaveImage"
      },
      "widgets_values": [
        "img"
      ]
    },
    {
      "id": 162,
      "type": "EmptySD3LatentImage",
      "pos": [
        -340.32689906004725,
        647.0619901743141
      ],
      "size": [
        250.61128906920487,
        106
      ],
      "flags": {},
      "order": 0,
      "mode": 0,
      "inputs": [],
      "outputs": [
        {
          "name": "LATENT",
          "type": "LATENT",
          "slot_index": 0,
          "links": [
            186
          ]
        }
      ],
      "properties": {
        "cnr_id": "comfy-core",
        "ver": "0.3.32",
        "Node name for S&R": "EmptySD3LatentImage"
      },
      "widgets_values": [
        768,
        768,
        1
      ],
      "color": "#323",
      "bgcolor": "#535"
    },
    {
      "id": 163,
      "type": "KSampler",
      "pos": [
        132.71229364851325,
        277.13973206727906
      ],
      "size": [
        296.2197989449314,
        262
      ],
      "flags": {},
      "order": 8,
      "mode": 0,
      "inputs": [
        {
          "name": "model",
          "type": "MODEL",
          "link": 225
        },
        {
          "name": "positive",
          "type": "CONDITIONING",
          "link": 223
        },
        {
          "name": "negative",
          "type": "CONDITIONING",
          "link": 220
        },
        {
          "name": "latent_image",
          "type": "LATENT",
          "link": 186
        }
      ],
      "outputs": [
        {
          "name": "LATENT",
          "type": "LATENT",
          "slot_index": 0,
          "links": [
            187
          ]
        }
      ],
      "properties": {
        "cnr_id": "comfy-core",
        "ver": "0.3.27",
        "Node name for S&R": "KSampler"
      },
      "widgets_values": [
        453348553937748,
        "randomize",
        5,
        1,
        "dpmpp_sde",
        "beta",
        1
      ]
    },
    {
      "id": 191,
      "type": "ModelSamplingAuraFlow",
      "pos": [
        -151.59813147779295,
        170.9075535482014
      ],
      "size": [
        270,
        58
      ],
      "flags": {},
      "order": 6,
      "mode": 0,
      "inputs": [
        {
          "name": "model",
          "type": "MODEL",
          "link": 235
        }
      ],
      "outputs": [
        {
          "name": "MODEL",
          "type": "MODEL",
          "links": [
            225
          ]
        }
      ],
      "properties": {
        "cnr_id": "comfy-core",
        "ver": "0.3.76",
        "Node name for S&R": "ModelSamplingAuraFlow"
      },
      "widgets_values": [
        3
      ]
    },
    {
      "id": 195,
      "type": "Note",
      "pos": [
        -500.84016606626926,
        37.8005851747157
      ],
      "size": [
        323.86169665440684,
        88
      ],
      "flags": {},
      "order": 1,
      "mode": 0,
      "inputs": [],
      "outputs": [],
      "title": "Lora Trigger Word",
      "properties": {},
      "widgets_values": [
        "pixag1rlwh1t3"
      ],
      "color": "#223",
      "bgcolor": "#335"
    },
    {
      "id": 6,
      "type": "CLIPTextEncode",
      "pos": [
        -510.6173893074787,
        301.16852260814346
      ],
      "size": [
        424.42708333333337,
        293.02083333333337
      ],
      "flags": {},
      "order": 5,
      "mode": 0,
      "inputs": [
        {
          "name": "clip",
          "type": "CLIP",
          "link": 232
        }
      ],
      "outputs": [
        {
          "name": "CONDITIONING",
          "type": "CONDITIONING",
          "slot_index": 0,
          "links": [
            219,
            223
          ]
        }
      ],
      "properties": {
        "cnr_id": "comfy-core",
        "ver": "0.3.27",
        "Node name for S&R": "CLIPTextEncode"
      },
      "widgets_values": [
        "pixag1rlwh1t3, portrait photo of a woman with white hair and green eyes looking at the camera and smiling, she wear a red dress"
      ],
      "color": "#232",
      "bgcolor": "#353"
    },
    {
      "id": 194,
      "type": "LoraLoaderModelOnly",
      "pos": [
        -501.4967748326585,
        170.44364185592474
      ],
      "size": [
        329.09839605484524,
        82
      ],
      "flags": {},
      "order": 4,
      "mode": 0,
      "inputs": [
        {
          "name": "model",
          "type": "MODEL",
          "link": 234
        }
      ],
      "outputs": [
        {
          "name": "MODEL",
          "type": "MODEL",
          "links": [
            235
          ]
        }
      ],
      "properties": {
        "cnr_id": "comfy-core",
        "ver": "0.3.76",
        "Node name for S&R": "LoraLoaderModelOnly"
      },
      "widgets_values": [
        "pixag1rlwh1t3.safetensors",
        0.8
      ],
      "color": "#223",
      "bgcolor": "#335"
    },
    {
      "id": 196,
      "type": "MarkdownNote",
      "pos": [
        -1063.2464349266445,
        428.1918606251212
      ],
      "size": [
        522.5104681185472,
        533.1759824449326
      ],
      "flags": {
        "collapsed": false
      },
      "order": 2,
      "mode": 0,
      "inputs": [],
      "outputs": [],
      "title": "👑 Pixaroma - Note - START HERE",
      "properties": {},
      "widgets_values": [
        "# MODELS AND NODES USED IN THIS WORKFLOW  \n\n---\n\n## 🟣 Load Checkpoint\n### Download **z-image-turbo-fp8-aio.safetensors** ~10GB from [HERE](https://huggingface.co/SeeSee21/Z-Image-Turbo-AIO/resolve/main/z-image-turbo-fp8-aio.safetensors?download=true)\n\n### Or \n\n### Download **z-image-turbo-bf16-aio.safetensors** ~20 GB from [HERE](https://huggingface.co/SeeSee21/Z-Image-Turbo-AIO/resolve/main/z-image-turbo-bf16-aio.safetensors?download=true)\n\n📁 **Place in:** `ComfyUI/models/checkpoints/z-image` \n\nCreate the `z-image` folder if it does not exist)\n \nMore info about the AIO models [HERE](https://huggingface.co/SeeSee21/Z-Image-Turbo-AIO)\n\n---\n\n## 🟣 LoraLoaderModelOnly\n\n### Download the **pixag1rlwh1t3.safetensors** from [HERE](https://huggingface.co/Pixaroma/experimental_loras/resolve/main/pixag1rlwh1t3.safetensors?download=true)  \n\n📁 **Place in:** `ComfyUI/models/loras/zimage`  \n\nCreate the `z-image` folder if it does not exist)\n\n---\n\n## 🧩 Nodes Installed from Manager  \n\n- None\n\n---\n\n## 📚 Resources  \n🎥 **Tutorials:** [Pixaroma YouTube Channel](https://www.youtube.com/@pixaroma)  \n💬 **Community Discord:** [Join Here](https://discord.com/invite/gggpkVgBf3)\n"
      ],
      "color": "#432",
      "bgcolor": "#653"
    },
    {
      "id": 193,
      "type": "CheckpointLoaderSimple",
      "pos": [
        -1063.7233029657566,
        282.69066060772724
      ],
      "size": [
        524.1231330948342,
        98
      ],
      "flags": {},
      "order": 3,
      "mode": 0,
      "inputs": [],
      "outputs": [
        {
          "name": "MODEL",
          "type": "MODEL",
          "links": [
            234
          ]
        },
        {
          "name": "CLIP",
          "type": "CLIP",
          "links": [
            232
          ]
        },
        {
          "name": "VAE",
          "type": "VAE",
          "links": [
            233
          ]
        }
      ],
      "properties": {
        "cnr_id": "comfy-core",
        "ver": "0.3.76",
        "Node name for S&R": "CheckpointLoaderSimple"
      },
      "widgets_values": [
        "z-image\\z-image-turbo-fp8-aio.safetensors"
      ]
    }
  ],
  "links": [
    [
      186,
      162,
      0,
      163,
      3,
      "LATENT"
    ],
    [
      187,
      163,
      0,
      164,
      0,
      "LATENT"
    ],
    [
      201,
      164,
      0,
      171,
      0,
      "IMAGE"
    ],
    [
      219,
      6,
      0,
      190,
      0,
      "CONDITIONING"
    ],
    [
      220,
      190,
      0,
      163,
      2,
      "CONDITIONING"
    ],
    [
      223,
      6,
      0,
      163,
      1,
      "CONDITIONING"
    ],
    [
      225,
      191,
      0,
      163,
      0,
      "MODEL"
    ],
    [
      232,
      193,
      1,
      6,
      0,
      "CLIP"
    ],
    [
      233,
      193,
      2,
      164,
      1,
      "VAE"
    ],
    [
      234,
      193,
      0,
      194,
      0,
      "MODEL"
    ],
    [
      235,
      194,
      0,
      191,
      0,
      "MODEL"
    ]
  ],
  "groups": [],
  "config": {},
  "extra": {
    "ds": {
      "scale": 0.8390545288824066,
      "offset": [
        1303.3187149536275,
        191.2329318884916
      ]
    },
    "frontendVersion": "1.33.10",
    "node_versions": {
      "ComfyUI-GGUF": "8098c7149fa4ff14991eb3347a5585051ceeafbe",
      "comfy-core": "v0.3.10-37-gd055325",
      "rgthree-comfy": "5d771b8b56a343c24a26e8cea1f0c87c3d58102f"
    },
    "VHS_latentpreview": false,
    "VHS_latentpreviewrate": 0,
    "VHS_MetadataImage": true,
    "VHS_KeepIntermediate": true,
    "workflowRendererVersion": "LG"
  },
  "version": 0.4
}